{
  "code": 200,
  "message": "Users fetched",
  "result": [
    {
      "id": "00000000-0000-0000-0000-000000000001",
      "username": "admin",
      "firstName": "System",
      "lastName": "Admin",
      "dob": "1990-01-01",
      "roles": [
        {
          "name": "ADMIN",
          "description": "Admin role",
          "permissions": []
        }
      ]
    },
    {
      "id": "00000000-0000-0000-0000-000000000002",
      "username": "sv.nguyenvana",
      "firstName": "Nguyen",
      "lastName": "Van A",
      "dob": "2004-03-15",
      "roles": [
        {
          "name": "STUDENT",
          "description": "Student role",
          "permissions": []
        }
      ]
    },
    {
      "id": "00000000-0000-0000-0000-000000000003",
      "username": "staff.ttb",
      "firstName": "Tran",
      "lastName": "Thi B",
      "dob": "1992-06-10",
      "roles": [
        {
          "name": "STAFF",
          "description": "Staff role",
          "permissions": []
        }
      ]
    },
    {
      "id": "00000000-0000-0000-0000-000000000004",
      "username": "sv.lethic",
      "firstName": "Le",
      "lastName": "Thi C",
      "dob": "2004-11-20",
      "roles": [
        {
          "name": "STUDENT",
          "description": "Student role",
          "permissions": []
        }
      ]
    }
  ]
}